LICENSE
MANIFEST.in
readme.md
setup.py
sensei2/__init__.py
sensei2.egg-info/PKG-INFO
sensei2.egg-info/SOURCES.txt
sensei2.egg-info/dependency_links.txt
sensei2.egg-info/requires.txt
sensei2.egg-info/top_level.txt
sensei2/management/__init__.py
sensei2/management/__init__.pyc
sensei2/management/commands/__init__.py
sensei2/management/commands/__init__.pyc
sensei2/management/commands/fill.py
sensei2/management/commands/fill.pyc
sensei2/plugins/__init__.py
sensei2/plugins/independent_pretty_tittle.py
sensei2/plugins/pretty_title.py
sensei2/plugins/youtube.py
sensei2/sensei/TODO
sensei2/sensei/__init__.py
sensei2/sensei/__init__.pyc
sensei2/sensei/exceptions.py
sensei2/sensei/exceptions.pyc
sensei2/sensei/field_handlers.py
sensei2/sensei/field_handlers.pyc
sensei2/sensei/helpers.py
sensei2/sensei/helpers.pyc
sensei2/sensei/sensei_room.py
sensei2/sensei/sensei_room.pyc
sensei2/sensei/fill_data/vesna.py
sensei2/sensei/fill_data/result/cities.txt
sensei2/sensei/fill_data/result/countries.txt
sensei2/sensei/fill_data/result/currency.txt
sensei2/sensei/fill_data/result/names.txt
sensei2/sensei/fill_data/result/paragraphs.txt
sensei2/sensei/fill_data/result/patronymics.txt
sensei2/sensei/fill_data/result/subjects.txt
sensei2/sensei/fill_data/result/surnames.txt
sensei2/sensei/handlers/__init__.py
sensei2/sensei/handlers/__init__.pyc
sensei2/sensei/handlers/base.py
sensei2/sensei/handlers/base.pyc
sensei2/sensei/handlers/date_and_time.py
sensei2/sensei/handlers/date_and_time.pyc
sensei2/sensei/handlers/files.py
sensei2/sensei/handlers/files.pyc
sensei2/sensei/handlers/joins.py
sensei2/sensei/handlers/joins.pyc
sensei2/sensei/handlers/numerical.py
sensei2/sensei/handlers/numerical.pyc
sensei2/sensei/handlers/text.py
sensei2/sensei/handlers/text.pyc