Metadata-Version: 1.0
Name: sensei2
Version: 1.1.2
Summary: A tool to fill your database with random, but logical data
Home-page: https://bitbucket.org/dvebukvy/sensei2/
Author: kirill
Author-email: kirillkostuykhin@me.com
License: DB
Platform: UNKNOWN
